bento_meta/CYPHER_QUERY_LOCATIONS.md
bento_meta/__init__.py
bento_meta/entity.py
bento_meta/model.py
bento_meta/object_map.py
bento_meta/objects.py
bento_meta/tf_objects.py
bento_meta/logs/log.ini
bento_meta/mdb/__init__.py
bento_meta/mdb/loaders.py
bento_meta/mdb/mdb.py
bento_meta/mdb/searchable.py
bento_meta/mdb/writeable.py
bento_meta/mdb/mdb_tools/__init__.py
bento_meta/mdb/mdb_tools/mdb_tools.py
bento_meta/util/__init__.py
bento_meta/util/_engine.py
bento_meta/util/makeq.py
bento_meta-0.3.1.dist-info/METADATA
bento_meta-0.3.1.dist-info/WHEEL
bento_meta-0.3.1.dist-info/entry_points.txt
bento_meta-0.3.1.dist-info/licenses/LICENSE
bento_meta-0.3.1.dist-info/RECORD
